setup.py
zippy/__init__.py
zippy/core.py
zippy.egg-info/PKG-INFO
zippy.egg-info/SOURCES.txt
zippy.egg-info/dependency_links.txt
zippy.egg-info/requires.txt
zippy.egg-info/top_level.txt